odoo/addons/account_invoice_supplierinfo_update_triple_discount/README.rst
odoo/addons/account_invoice_supplierinfo_update_triple_discount/__init__.py
odoo/addons/account_invoice_supplierinfo_update_triple_discount/__manifest__.py
odoo/addons/account_invoice_supplierinfo_update_triple_discount/i18n/account_invoice_supplierinfo_update_triple_discount.pot
odoo/addons/account_invoice_supplierinfo_update_triple_discount/i18n/es.po
odoo/addons/account_invoice_supplierinfo_update_triple_discount/i18n/fr.po
odoo/addons/account_invoice_supplierinfo_update_triple_discount/i18n/it.po
odoo/addons/account_invoice_supplierinfo_update_triple_discount/models/__init__.py
odoo/addons/account_invoice_supplierinfo_update_triple_discount/models/account_move_line.py
odoo/addons/account_invoice_supplierinfo_update_triple_discount/readme/CONTRIBUTORS.rst
odoo/addons/account_invoice_supplierinfo_update_triple_discount/readme/DESCRIPTION.rst
odoo/addons/account_invoice_supplierinfo_update_triple_discount/static/description/icon.png
odoo/addons/account_invoice_supplierinfo_update_triple_discount/static/description/index.html
odoo/addons/account_invoice_supplierinfo_update_triple_discount/static/description/wizard_form.png
odoo/addons/account_invoice_supplierinfo_update_triple_discount/tests/__init__.py
odoo/addons/account_invoice_supplierinfo_update_triple_discount/tests/test_module.py
odoo/addons/account_invoice_supplierinfo_update_triple_discount/wizard/__init__.py
odoo/addons/account_invoice_supplierinfo_update_triple_discount/wizard/wizard_update_invoice_supplierinfo.py
odoo/addons/account_invoice_supplierinfo_update_triple_discount/wizard/wizard_update_invoice_supplierinfo.xml
odoo/addons/account_invoice_supplierinfo_update_triple_discount/wizard/wizard_update_invoice_supplierinfo_line.py
odoo_addon_account_invoice_supplierinfo_update_triple_discount-16.0.1.0.1.1.dist-info/METADATA
odoo_addon_account_invoice_supplierinfo_update_triple_discount-16.0.1.0.1.1.dist-info/WHEEL
odoo_addon_account_invoice_supplierinfo_update_triple_discount-16.0.1.0.1.1.dist-info/top_level.txt
odoo_addon_account_invoice_supplierinfo_update_triple_discount-16.0.1.0.1.1.dist-info/RECORD
