Metadata-Version: 2.1
Name: odoo-addon-account_invoice_supplierinfo_update_triple_discount
Version: 16.0.1.0.1.1
Summary: In the supplier invoice, automatically update all products whose discounts on the line is different from the supplier discounts
Home-page: https://github.com/OCA/account-invoicing
Author: GRAP,Odoo Community Association (OCA)
Author-email: support@odoo-community.org
License: AGPL-3
Classifier: Programming Language :: Python
Classifier: Framework :: Odoo
Classifier: Framework :: Odoo :: 16.0
Classifier: License :: OSI Approved :: GNU Affero General Public License v3
Requires-Python: >=3.10
Requires-Dist: odoo-addon-account-invoice-supplierinfo-update-discount <16.1dev,>=16.0dev
Requires-Dist: odoo-addon-account-invoice-triple-discount <16.1dev,>=16.0dev
Requires-Dist: odoo-addon-purchase-triple-discount <16.1dev,>=16.0dev
Requires-Dist: odoo <16.1dev,>=16.0a
